{
  "schema": "profile.json",
  "crd": {
    "group": "network.azure.m.upbound.io",
    "kind": "Profile",
    "apiVersion": "v1beta1"
  },
  "source": {
    "name": "provider-upjet-azure",
    "type": "git+github",
    "repo": "https://github.com/crossplane-contrib/provider-upjet-azure",
    "path": "package/crds",
    "version": "v2.5.0",
    "license": "Apache-2.0",
    "homepage": "https://marketplace.upbound.io/providers/upbound/provider-family-azure"
  },
  "extraction": {
    "timestamp": "2026-03-20T19:02:52Z",
    "toolVersion": "crd-schema-extractor v0.1.0"
  },
  "integrity": {
    "sha256": "00473beeda818d2f0b3911adaa10d4241d86b0599572e7d940a78981828047b4"
  }
}