{
  "schema": "webapplicationfirewallpolicy.json",
  "crd": {
    "group": "network.azure.m.upbound.io",
    "kind": "WebApplicationFirewallPolicy",
    "apiVersion": "v1beta1"
  },
  "source": {
    "name": "provider-upjet-azure",
    "type": "git+github",
    "repo": "https://github.com/crossplane-contrib/provider-upjet-azure",
    "path": "package/crds",
    "version": "v2.5.0",
    "license": "Apache-2.0",
    "homepage": "https://marketplace.upbound.io/providers/upbound/provider-family-azure"
  },
  "extraction": {
    "timestamp": "2026-03-20T19:02:52Z",
    "toolVersion": "crd-schema-extractor v0.1.0"
  },
  "integrity": {
    "sha256": "4af6b83d100b1a207cedebd8064dc6c427edafc54111c996f2ab7f8faa8195af"
  }
}