{
  "schema": "keygroup.json",
  "crd": {
    "group": "cloudfront.aws.upbound.io",
    "kind": "KeyGroup",
    "apiVersion": "v1beta1"
  },
  "source": {
    "name": "provider-upjet-aws",
    "type": "git+github",
    "repo": "https://github.com/crossplane-contrib/provider-upjet-aws",
    "path": "package/crds",
    "version": "v2.5.0",
    "license": "Apache-2.0",
    "homepage": "https://marketplace.upbound.io/providers/upbound/provider-family-aws"
  },
  "extraction": {
    "timestamp": "2026-03-20T19:02:52Z",
    "toolVersion": "crd-schema-extractor v0.1.0"
  },
  "integrity": {
    "sha256": "a6d6ee4d7a47e26b5f4260738f7e2274a5fc225df27f749517a5e9e60d01a9f8"
  }
}