{
  "schema": "ipamconfig.json",
  "crd": {
    "group": "crd.projectcalico.org",
    "kind": "IPAMConfig",
    "apiVersion": "v1"
  },
  "source": {
    "name": "tigera-operator",
    "type": "helm",
    "repo": "https://docs.tigera.io/calico/charts",
    "chart": "tigera-operator",
    "version": "v3.31.4",
    "license": "Apache-2.0",
    "homepage": "https://www.tigera.io/project-calico",
    "include": [
      "crd.projectcalico.org/*"
    ]
  },
  "extraction": {
    "timestamp": "2026-03-05T11:37:31Z",
    "toolVersion": "crd-schemas v0.1.0"
  },
  "integrity": {
    "sha256": "ae17fdc19132fad48a93fbf40892a7f32a603eab7a4cfe3b7707a351ceb61ac4"
  }
}