{
  "schema": "replicationconfiguration.json",
  "crd": {
    "group": "efs.aws.m.upbound.io",
    "kind": "ReplicationConfiguration",
    "apiVersion": "v1beta1"
  },
  "source": {
    "name": "provider-upjet-aws",
    "type": "git+github",
    "repo": "https://github.com/crossplane-contrib/provider-upjet-aws",
    "path": "package/crds",
    "version": "v2.5.0",
    "license": "Apache-2.0",
    "homepage": "https://marketplace.upbound.io/providers/upbound/provider-family-aws"
  },
  "extraction": {
    "timestamp": "2026-03-20T19:02:52Z",
    "toolVersion": "crd-schema-extractor v0.1.0"
  },
  "integrity": {
    "sha256": "2113a24022855e7ff1386ff40b34b0846ae4d18f2ca25b88029a3cccf49db10d"
  }
}