{
  "schema": "instance.json",
  "crd": {
    "group": "ec2.aws.upbound.io",
    "kind": "Instance",
    "apiVersion": "v1beta2"
  },
  "source": {
    "name": "provider-upjet-aws",
    "type": "git+github",
    "repo": "https://github.com/crossplane-contrib/provider-upjet-aws",
    "path": "package/crds",
    "version": "v2.5.0",
    "license": "Apache-2.0",
    "homepage": "https://marketplace.upbound.io/providers/upbound/provider-family-aws"
  },
  "extraction": {
    "timestamp": "2026-03-20T19:02:52Z",
    "toolVersion": "crd-schema-extractor v0.1.0"
  },
  "integrity": {
    "sha256": "d341a00fbe2741faaaa3e6bdfbc231dd77f520e273f6f3c88e9edfb3d8b12ff8"
  }
}