{
  "schema": "domain.json",
  "crd": {
    "group": "codeartifact.aws.m.upbound.io",
    "kind": "Domain",
    "apiVersion": "v1beta1"
  },
  "source": {
    "name": "provider-upjet-aws",
    "type": "git+github",
    "repo": "https://github.com/crossplane-contrib/provider-upjet-aws",
    "path": "package/crds",
    "version": "v2.5.0",
    "license": "Apache-2.0",
    "homepage": "https://marketplace.upbound.io/providers/upbound/provider-family-aws"
  },
  "extraction": {
    "timestamp": "2026-03-20T19:02:52Z",
    "toolVersion": "crd-schema-extractor v0.1.0"
  },
  "integrity": {
    "sha256": "2cd63b9aab4acdf70b9289ba5d4b05f1bd602026b80efb58846ec9bac8a3ba15"
  }
}