{
  "schema": "activity.json",
  "crd": {
    "group": "sfn.aws.upbound.io",
    "kind": "Activity",
    "apiVersion": "v1beta1"
  },
  "source": {
    "name": "provider-upjet-aws",
    "type": "git+github",
    "repo": "https://github.com/crossplane-contrib/provider-upjet-aws",
    "path": "package/crds",
    "version": "v2.5.0",
    "license": "Apache-2.0",
    "homepage": "https://marketplace.upbound.io/providers/upbound/provider-family-aws"
  },
  "extraction": {
    "timestamp": "2026-03-20T19:02:52Z",
    "toolVersion": "crd-schema-extractor v0.1.0"
  },
  "integrity": {
    "sha256": "4cab9569a9eeb9492a7e06d3a665173b1614b98982c42e3fbcc2f6130023a04f"
  }
}