{
  "schema": "clusterworkflowtemplate.json",
  "crd": {
    "group": "argoproj.io",
    "kind": "ClusterWorkflowTemplate",
    "apiVersion": "v1alpha1"
  },
  "source": {
    "name": "argo-workflows",
    "type": "helm",
    "repo": "https://argoproj.github.io/argo-helm",
    "chart": "argo-workflows",
    "version": "0.47.4",
    "license": "Apache-2.0",
    "homepage": "https://argoproj.github.io/workflows",
    "include": [
      "ClusterWorkflowTemplate",
      "CronWorkflow",
      "Workflow",
      "WorkflowArtifactGCTask",
      "WorkflowEventBinding",
      "WorkflowTaskResult",
      "WorkflowTaskSet",
      "WorkflowTemplate"
    ]
  },
  "extraction": {
    "timestamp": "2026-03-05T11:37:31Z",
    "toolVersion": "crd-schemas v0.1.0"
  },
  "integrity": {
    "sha256": "c7b3447af1ea539c42e93fb3bf9d113eeabfdaf92e656c4e811dae20ad1c4c93"
  }
}