{
  "schema": "vault.json",
  "crd": {
    "group": "glacier.aws.upbound.io",
    "kind": "Vault",
    "apiVersion": "v1beta1"
  },
  "source": {
    "name": "provider-upjet-aws",
    "type": "git+github",
    "repo": "https://github.com/crossplane-contrib/provider-upjet-aws",
    "path": "package/crds",
    "version": "v2.5.0",
    "license": "Apache-2.0",
    "homepage": "https://marketplace.upbound.io/providers/upbound/provider-family-aws"
  },
  "extraction": {
    "timestamp": "2026-03-20T19:02:52Z",
    "toolVersion": "crd-schema-extractor v0.1.0"
  },
  "integrity": {
    "sha256": "38fdf7d6b3be0cfdaa3f0e773b9f8a75ea383c2b8710551f9cdd8e52c7bb0ca7"
  }
}