{
  "schema": "scrapeconfig.json",
  "crd": {
    "group": "monitoring.coreos.com",
    "kind": "ScrapeConfig",
    "apiVersion": "v1alpha1"
  },
  "source": {
    "name": "prometheus-operator",
    "type": "helm",
    "repo": "https://prometheus-community.github.io/helm-charts",
    "chart": "kube-prometheus-stack",
    "version": "v69.8.2",
    "license": "Apache-2.0",
    "homepage": "https://prometheus-operator.dev"
  },
  "extraction": {
    "timestamp": "2026-03-05T09:57:11Z",
    "toolVersion": "crd-schemas v0.1.0"
  },
  "integrity": {
    "sha256": "7108165cd5224243ba4997e2f1acfd5aee56aae545e89a5a5e628ebbe593beb9"
  }
}